Metadata-Version: 1.0
Name: distributions-mango
Version: 0.1
Summary: Gaussian distributions and Binomial Distributions
Home-page: UNKNOWN
Author: UNKNOWN
Author-email: UNKNOWN
License: UNKNOWN
Platform: UNKNOWN
